MANIFEST.in
README.txt
setup.py
docs/HISTORY.txt
docs/LICENSE.txt
src/silva/__init__.py
src/silva.core.xml.egg-info/PKG-INFO
src/silva.core.xml.egg-info/SOURCES.txt
src/silva.core.xml.egg-info/dependency_links.txt
src/silva.core.xml.egg-info/entry_points.txt
src/silva.core.xml.egg-info/namespace_packages.txt
src/silva.core.xml.egg-info/not-zip-safe
src/silva.core.xml.egg-info/requires.txt
src/silva.core.xml.egg-info/top_level.txt
src/silva/core/__init__.py
src/silva/core/xml/__init__.py
src/silva/core/xml/configure.zcml
src/silva/core/xml/defaulthandlers.py
src/silva/core/xml/handlers.py
src/silva/core/xml/martiansupport.py
src/silva/core/xml/producers.py
src/silva/core/xml/xmlexport.py
src/silva/core/xml/xmlimport.py