Metadata-Version: 1.1
Name: silva.core.xml
Version: 3.0.1
Summary: Support to export Silva content into XML
Home-page: https://github.com/silvacms/silva.core.xml
Author: Infrae
Author-email: info@infrae.com
License: BSD
Keywords: silva core xml export import
Platform: UNKNOWN
Classifier: Framework :: Zope2
Classifier: License :: OSI Approved :: BSD License
Classifier: Programming Language :: Python
Classifier: Topic :: Software Development :: Libraries :: Python Modules
